orchestrix/py.typed
orchestrix/core/__init__.py
orchestrix/core/common/__init__.py
orchestrix/core/common/exceptions.py
orchestrix/core/common/logging.py
orchestrix/core/common/module.py
orchestrix/core/common/observability.py
orchestrix/core/common/retry.py
orchestrix/core/common/validation.py
orchestrix/core/eventsourcing/__init__.py
orchestrix/core/eventsourcing/aggregate.py
orchestrix/core/eventsourcing/event_store.py
orchestrix/core/eventsourcing/projection.py
orchestrix/core/eventsourcing/snapshot.py
orchestrix/core/eventsourcing/versioning.py
orchestrix/core/execution/__init__.py
orchestrix/core/execution/saga.py
orchestrix/core/messaging/__init__.py
orchestrix/core/messaging/command_handler.py
orchestrix/core/messaging/dead_letter_queue.py
orchestrix/core/messaging/message.py
orchestrix/core/messaging/message_bus.py
orchestrix/infrastructure/__init__.py
orchestrix/infrastructure/eventsourcingdb/__init__.py
orchestrix/infrastructure/eventsourcingdb/store.py
orchestrix/infrastructure/memory/__init__.py
orchestrix/infrastructure/memory/async_bus.py
orchestrix/infrastructure/memory/async_store.py
orchestrix/infrastructure/memory/bus.py
orchestrix/infrastructure/memory/store.py
orchestrix/infrastructure/memory/utils.py
orchestrix/infrastructure/observability/__init__.py
orchestrix/infrastructure/observability/jaeger.py
orchestrix/infrastructure/observability/prometheus.py
orchestrix/infrastructure/postgres/__init__.py
orchestrix/infrastructure/postgres/connection_pool.py
orchestrix/infrastructure/postgres/store.py
orchestrix/infrastructure/postgres/migrations/001_postgres_schema.sql
orchestrix/infrastructure/postgres/migrations/001_postgres_schema_rollback.sql
orchestrix-0.1.0.dist-info/METADATA
orchestrix-0.1.0.dist-info/WHEEL
orchestrix-0.1.0.dist-info/licenses/LICENSE
orchestrix-0.1.0.dist-info/RECORD
