Metadata-Version: 2.4
Name: orchestrix
Version: 0.1.0
Summary: A modular, event-driven event sourcing library for Python. Orchestrix helps you build scalable, maintainable, and testable systems by combining event sourcing, CQRS, and asynchronous messaging in a architecture. Ideal for complex business domains, microservices, and distributed workflows.
Author-email: Stefan Poss <sp@stefanposs.com>
License: MIT License
License-File: LICENSE
Requires-Python: <3.14,>=3.12
Requires-Dist: eventsourcingdb==1.9.0
Requires-Dist: fastapi<1.0.0,>=0.110.0
Requires-Dist: httpx<1.0.0,>=0.25.0
Requires-Dist: jaeger-client<5.0.0,>=4.8.0
Requires-Dist: prometheus-client<1.0.0,>=0.17.0
Requires-Dist: psycopg[binary]<4.0.0,>=3.1.0
Requires-Dist: pydantic<3.0.0,>=2.0.0
Requires-Dist: typing-extensions<5.0.0,>=4.8.0
